Topsis/__init__.py
Topsis/__main__.py
Topsis_Aryan_102103140-1.1.2.dist-info/METADATA
Topsis_Aryan_102103140-1.1.2.dist-info/WHEEL
Topsis_Aryan_102103140-1.1.2.dist-info/entry_points.txt
Topsis_Aryan_102103140-1.1.2.dist-info/top_level.txt
Topsis_Aryan_102103140-1.1.2.dist-info/RECORD
