Metadata-Version: 2.1
Name: Topsis-Aryan-102103140
Version: 1.1.2
Summary: Topsis-Aryan-102103140
Home-page: https://github.com/AryanGupta30/Topsis-Aryan-102103140.git
Author: Aryan Gupta
Author-email: 30aryang@gmail.com
License: MIT
Classifier: License :: OSI Approved :: MIT License
Classifier: Programming Language :: Python :: 3.6
Classifier: Programming Language :: Python :: 3.7
Classifier: Programming Language :: Python :: 3.8
